mashell/__init__.py
mashell/__main__.py
mashell/cli.py
mashell/config.py
mashell/logo.py
mashell/session.py
mashell/agent/__init__.py
mashell/agent/context.py
mashell/agent/core.py
mashell/agent/prompt.py
mashell/integrations/__init__.py
mashell/integrations/slack.py
mashell/permissions/__init__.py
mashell/permissions/manager.py
mashell/permissions/ui.py
mashell/providers/__init__.py
mashell/providers/anthropic.py
mashell/providers/azure.py
mashell/providers/base.py
mashell/providers/ollama.py
mashell/providers/openai.py
mashell/tools/__init__.py
mashell/tools/background.py
mashell/tools/base.py
mashell/tools/filesystem.py
mashell/tools/shell.py
mashell/tools/web.py
mashell-1.0.10.dist-info/METADATA
mashell-1.0.10.dist-info/WHEEL
mashell-1.0.10.dist-info/entry_points.txt
mashell-1.0.10.dist-info/licenses/LICENSE
mashell-1.0.10.dist-info/RECORD
