Metadata-Version: 2.4
Name: mashell
Version: 1.0.10
Summary: AI-powered command line assistant - any model, anywhere
Author: Jacob
License: GPL-3.0
License-File: LICENSE
Keywords: agent,ai,assistant,cli,llm,shell
Classifier: Development Status :: 3 - Alpha
Classifier: Environment :: Console
Classifier: Intended Audience :: Developers
Classifier: License :: OSI Approved :: GNU General Public License v3 (GPLv3)
Classifier: Programming Language :: Python :: 3.11
Classifier: Programming Language :: Python :: 3.12
Classifier: Topic :: Software Development :: Libraries :: Python Modules
Requires-Python: >=3.11
Requires-Dist: crawl4ai>=0.8.0
Requires-Dist: httpx>=0.25.0
Requires-Dist: pdfplumber>=0.10.0
Requires-Dist: prompt-toolkit>=3.0
Requires-Dist: python-docx>=1.0.0
Requires-Dist: pyyaml>=6.0
Requires-Dist: rich>=13.0.0
Requires-Dist: slack-bolt>=1.18.0
Requires-Dist: slack-sdk>=3.21.0
Provides-Extra: dev
Requires-Dist: mypy>=1.0; extra == 'dev'
Requires-Dist: pytest-asyncio>=0.21; extra == 'dev'
Requires-Dist: pytest>=7.0; extra == 'dev'
Requires-Dist: ruff>=0.1.0; extra == 'dev'
Requires-Dist: types-pyyaml>=6.0; extra == 'dev'
